[
  {
    "title": "Single Malt Scotch",
    "type": "Spirit",
    "subType": "Single Malt",
    "alcohol": "43%",
    "price": "$70.00",
    "discount": "15",
    "capacity": "750ml",
    "iva": true,
    "imageURL": "",
    "imageID": ""
  },
  {
    "title": "Cabernet Sauvignon",
    "type": "Wine",
    "subType": "Red Wine",
    "alcohol": "14%",
    "price": "$25.00",
    "discount": "0",
    "capacity": "750ml",
    "iva": true,
    "imageURL": "",
    "imageID": ""
  },
  {
    "title": "Pinot Grigio",
    "type": "Wine",
    "subType": "White Wine",
    "alcohol": "12%",
    "price": "$20.00",
    "discount": "10",
    "capacity": "750ml",
    "iva": true,
    "imageURL": "",
    "imageID": ""
  },
  {
    "title": "India Pale Ale",
    "type": "Beer",
    "subType": "IPA",
    "alcohol": "6.5%",
    "price": "$8.00",
    "discount": "0",
    "capacity": "355ml",
    "iva": true,
    "imageURL": "",
    "imageID": ""
  }
]
